rnodeconf/__init__.py
rnodeconf/rnodeconf.py
rnodeconf-1.3.1.dist-info/LICENSE
rnodeconf-1.3.1.dist-info/METADATA
rnodeconf-1.3.1.dist-info/WHEEL
rnodeconf-1.3.1.dist-info/entry_points.txt
rnodeconf-1.3.1.dist-info/top_level.txt
rnodeconf-1.3.1.dist-info/RECORD
