Metadata-Version: 2.1
Name: rnodeconf
Version: 1.3.1
Summary: Configuration Utility for RNode hardware
Home-page: https://github.com/markqvist/rnodeconfigutil
Author: Mark Qvist
Author-email: mark@unsigned.io
Classifier: Programming Language :: Python :: 3
Classifier: License :: OSI Approved :: MIT License
Classifier: Operating System :: OS Independent
Requires-Python: >=3.6
License-File: LICENSE
Requires-Dist: pyserial (>=3.5)
Requires-Dist: cryptography
Requires-Dist: rns (>=0.3.18)
